arcflash/__init__.py
arcflash/ieee_1584/__init__.py
arcflash/ieee_1584/calculation.py
arcflash/ieee_1584/cubicle.py
arcflash/ieee_1584/equations.py
arcflash/ieee_1584/multistep.py
arcflash/ieee_1584/tables.py
arcflash/ieee_1584/units.py
arcflash/ieee_1584/tests/__init__.py
arcflash/ieee_1584/tests/example_ieee_1584_calcs.py
arcflash/ieee_1584/tests/test_example_calcs.py
arcflash/ieee_1584/tests/test_multistep.py
arcflash_calc-0.1.0.dist-info/LICENSE.txt
arcflash_calc-0.1.0.dist-info/WHEEL
arcflash_calc-0.1.0.dist-info/METADATA
arcflash_calc-0.1.0.dist-info/RECORD
