Metadata-Version: 2.1
Name: arcflash-calc
Version: 0.1.0
Summary: Performs arc flash calculations, using IEEE 1584 and other methods.
Author-email: Li-aung Yip <github@penwatch.net>
Requires-Python: >=3.7
Classifier: License :: OSI Approved :: MIT License
Requires-Dist: pint >= 0.20.1
Project-URL: Source, https://github.com/LiaungYip/arcflash
